{
  "cli": {
    "version": ">= 7.3.0",
    "requireCommit": true
  },
  "build": {
    "development": {
      "developmentClient": false,
      "distribution": "internal",
      "channel": "development"
    },
    "preview": {
      "distribution": "internal",
      "android": {
        "buildType": "apk"
      },
      "ios": {
        "simulator": "true"
      },
      "channel": "preview"
    },
    "production": {
      "channel": "production"
    }
  },
  "submit": {
    "production": {}
  }
}
